langevals_custom/basic.py
langevals_custom/llm_boolean.py
langevals_custom/llm_score.py
langevals_custom/similarity.py
langevals_custom-0.1.3.dist-info/METADATA
langevals_custom-0.1.3.dist-info/WHEEL
langevals_custom-0.1.3.dist-info/RECORD
