Metadata-Version: 2.1
Name: langevals-custom
Version: 0.1.3
Summary: Custom evaluators you can build using other LLMs to do the eval, semantic matching or simple regexes or string matching.
License: MIT
Author: Rogerio Chaves
Author-email: rogerio@langwatch.ai
Requires-Python: >=3.11,<4.0
Classifier: License :: OSI Approved :: MIT License
Classifier: Programming Language :: Python :: 3
Classifier: Programming Language :: Python :: 3.11
Classifier: Programming Language :: Python :: 3.12
Requires-Dist: langevals-core (>=0.1.4,<0.2.0)
Requires-Dist: litellm (>=1.31.3,<2.0.0)
Requires-Dist: numpy (>=1.26.4,<2.0.0)
